pysmiles/PTE.json
pysmiles/__init__.py
pysmiles/read_smiles.py
pysmiles/smiles_helper.py
pysmiles/testhelper.py
pysmiles/write_smiles.py
pysmiles-2.0.1.dist-info/licenses/LICENSE.md
pysmiles-2.0.1.dist-info/METADATA
pysmiles-2.0.1.dist-info/WHEEL
pysmiles-2.0.1.dist-info/pbr.json
pysmiles-2.0.1.dist-info/top_level.txt
pysmiles-2.0.1.dist-info/RECORD
