Metadata-Version: 2.4
Name: pysmiles
Version: 2.0.1
Summary: A lightweight SMILES reader and writer
Home-page: https://github.com/pckroon/pysmiles
Author: P C Kroon
Author-email: p.c.kroon@rug.nl
License: Apache 2.0
Keywords: SMILES cheminformatics chemistry
Classifier: Development Status :: 4 - Beta
Classifier: Intended Audience :: Developers
Classifier: Intended Audience :: Science/Research
Classifier: License :: OSI Approved :: Apache Software License
Classifier: Operating System :: OS Independent
Classifier: Programming Language :: Python :: 3
Classifier: Topic :: Scientific/Engineering :: Bio-Informatics
Classifier: Topic :: Scientific/Engineering :: Chemistry
License-File: LICENSE.md
Requires-Dist: pbr
Requires-Dist: networkx~=3.0
Dynamic: author
Dynamic: author-email
Dynamic: classifier
Dynamic: description
Dynamic: description-content-type
Dynamic: keywords
Dynamic: license
Dynamic: license-file
Dynamic: summary
